succulent/__init__.py
succulent/api.py
succulent/configuration.py
succulent/processing.py
succulent/static/logo.png
succulent-0.4.3.dist-info/LICENSE
succulent-0.4.3.dist-info/METADATA
succulent-0.4.3.dist-info/WHEEL
succulent-0.4.3.dist-info/RECORD
