Metadata-Version: 2.1
Name: succulent
Version: 0.4.3
Summary: Collect POST requests easily
Home-page: https://github.com/firefly-cpp/succulent
License: MIT
Keywords: data collection,data science,ESP32,sensor measurements,smart agriculture,smartwatch
Author: Iztok Fister Jr.
Author-email: iztok@iztok-jr-fister.eu
Requires-Python: >=3.10,<4.0
Classifier: License :: OSI Approved :: MIT License
Classifier: Programming Language :: Python :: 3
Classifier: Programming Language :: Python :: 3.10
Classifier: Programming Language :: Python :: 3.11
Classifier: Programming Language :: Python :: 3.12
Classifier: Programming Language :: Python :: 3.13
Requires-Dist: flask (>=2.3.2,<3.0.0)
Requires-Dist: lxml (>=5.2.2,<6.0.0)
Requires-Dist: numpy (==2.1.0)
Requires-Dist: pandas (>=2.0.1,<3.0.0)
Requires-Dist: pyyaml (>=6.0,<7.0)
Project-URL: Documentation, https://succulent.readthedocs.io/en/latest/
Project-URL: Repository, https://github.com/firefly-cpp/succulent
